WSUAutograder/__init__.py
WSUAutograder/_utils.py
WSUAutograder/program.py
WSUAutograder/smartGrader.py
wsu_autograder-1.0.1.dist-info/LICENSE
wsu_autograder-1.0.1.dist-info/METADATA
wsu_autograder-1.0.1.dist-info/WHEEL
wsu_autograder-1.0.1.dist-info/entry_points.txt
wsu_autograder-1.0.1.dist-info/top_level.txt
wsu_autograder-1.0.1.dist-info/RECORD
