Metadata-Version: 2.1
Name: wsu-autograder
Version: 1.0.1
Summary: An intelligent autograder tool written and used by the Wright State University CECS department
Home-page: https://github.com/wrightedu/autograder
Author: WSU CECS, Owen O'Connor
Author-email: cse-support@wright.edu
License: MIT
Keywords: grading,automation,wright state university
Platform: UNKNOWN
Classifier: License :: OSI Approved :: MIT License
Classifier: Development Status :: 4 - Beta
Classifier: Environment :: Console
Classifier: Intended Audience :: Education
Classifier: Natural Language :: English
Classifier: Operating System :: OS Independent
Classifier: Programming Language :: Python :: 3 :: Only
Classifier: Topic :: Education :: Computer Aided Instruction (CAI)
Requires-Dist: binaryornot
Requires-Dist: lark-parser
Requires-Dist: Pygments
Requires-Dist: tqdm
